redflyingbaron.py
redflyingbaron-0.1.1.dist-info/metadata.json
redflyingbaron-0.1.1.dist-info/METADATA
redflyingbaron-0.1.1.dist-info/WHEEL
redflyingbaron-0.1.1.dist-info/RECORD
redflyingbaron-0.1.1.dist-info/top_level.txt
redflyingbaron-0.1.1.dist-info/entry_points.txt
redflyingbaron-0.1.1.dist-info/DESCRIPTION.rst
