Metadata-Version: 2.0
Name: redflyingbaron
Version: 0.1.1
Summary: Project wrapper arround RedBaron
Home-page: https://github.com/Psycojoker/redflyingbaron
Author: Laurent Peuch
Author-email: cortex@worlddomination.be
License: lGPLv3+
Keywords: baron redbaron refactoring editor ast fst
Platform: UNKNOWN
Classifier: Development Status :: 3 - Alpha
Classifier: Intended Audience :: Developers
Classifier: License :: OSI Approved :: GNU Lesser General Public License v3 (LGPLv3)
Classifier: Topic :: Software Development
Classifier: Topic :: Software Development :: Code Generators
Requires-Dist: baron (>=0.6.1)
Requires-Dist: redbaron (>=0.5)
Requires-Dist: ipython
